sort_pipe.v
module sort_pipe(
    input clk,
    input  [7:0] x_0,x_1,x_2,x_3,x_4,x_5,x_6,x_7,x_8,
    output [7:0] median,
    output [7:0] r0_out0
);


    reg[7:0] r0 [8:0];
    reg[7:0] r1 [8:0];
    reg[7:0] r2 [8:0];
    reg[7:0] r3 [8:0];
    reg[7:0] r4 [8:0];
    reg[7:0] r5 [8:0];
    reg[7:0] r6 [8:0];
    reg[7:0] r7 [8:0];

    assign r0_out0 = r0[0];

    wire [7:0] cmp1_out0;
    wire [7:0] cmp1_out1;
    reg [7:0] cmp1_in0;
    reg [7:0] cmp1_in1;

    wire [7:0] cmp2_out0;
    wire [7:0] cmp2_out1;
    reg [7:0] cmp2_in0;
    reg [7:0] cmp2_in1;

    wire [7:0] cmp3_out0;
    wire [7:0] cmp3_out1;
    reg [7:0] cmp3_in0;
    reg [7:0] cmp3_in1;

    wire [7:0] cmp4_out0;
    wire [7:0] cmp4_out1;
    reg [7:0] cmp4_in0;
    reg [7:0] cmp4_in1;

    wire [7:0] cmp5_out0;
    wire [7:0] cmp5_out1;
    reg [7:0] cmp5_in0;
    reg [7:0] cmp5_in1;

    wire [7:0] cmp6_out0;
    wire [7:0] cmp6_out1;
    reg [7:0] cmp6_in0;
    reg [7:0] cmp6_in1;

    wire [7:0] cmp7_out0;
    wire [7:0] cmp7_out1;
    reg [7:0] cmp7_in0;
    reg [7:0] cmp7_in1;

    wire [7:0] cmp8_out0;
    wire [7:0] cmp8_out1;
    reg [7:0] cmp8_in0;
    reg [7:0] cmp8_in1;

    wire [7:0] cmp9_out0;
    wire [7:0] cmp9_out1;
    reg [7:0] cmp9_in0;
    reg [7:0] cmp9_in1;
    
    wire [7:0] cmp10_out0;
    wire [7:0] cmp10_out1;
    reg [7:0] cmp10_in0;
    reg [7:0] cmp10_in1;

    wire [7:0] cmp11_out0;
    wire [7:0] cmp11_out1;
    reg [7:0] cmp11_in0;
    reg [7:0] cmp11_in1;
    
    wire [7:0] cmp12_out0;
    wire [7:0] cmp12_out1;
    reg [7:0] cmp12_in0;
    reg [7:0] cmp12_in1;

    wire [7:0] cmp13_out0;
    wire [7:0] cmp13_out1;
    reg [7:0] cmp13_in0;
    reg [7:0] cmp13_in1;

    wire [7:0] cmp14_out0;
    wire [7:0] cmp14_out1;
    reg [7:0] cmp14_in0;
    reg [7:0] cmp14_in1;

    wire [7:0] cmp15_out0;
    wire [7:0] cmp15_out1;
    reg [7:0] cmp15_in0;
    reg [7:0] cmp15_in1;

    wire [7:0] cmp16_out0;
    wire [7:0] cmp16_out1;
    reg [7:0] cmp16_in0;
    reg [7:0] cmp16_in1;

    wire [7:0] cmp17_out0;
    wire [7:0] cmp17_out1;
    reg [7:0] cmp17_in0;
    reg [7:0] cmp17_in1;

    wire [7:0] cmp18_out0;
    wire [7:0] cmp18_out1;
    reg [7:0] cmp18_in0;
    reg [7:0] cmp18_in1;

    wire [7:0] cmp19_out0;
    wire [7:0] cmp19_out1;
    reg [7:0] cmp19_in0;
    reg [7:0] cmp19_in1;

    reg[7:0] r02_tmp;
    reg[7:0] r05_tmp;
    reg[7:0] r08_tmp;
    reg[7:0] r10_tmp;
    reg[7:0] r13_tmp;
    reg[7:0] r16_tmp;
    reg[7:0] r22_tmp;
    reg[7:0] r25_tmp;
    reg[7:0] r28_tmp;
    reg[7:0] r32_tmp;
    reg[7:0] r35_tmp;
    reg[7:0] r36_tmp;
    reg[7:0] r43_tmp;
    reg[7:0] r52_tmp;
    reg[7:0] r56_tmp;
    reg[7:0] r65_tmp;
    reg[7:0] r73_tmp;

always @(posedge clk)begin

    cmp1_in0 <= x_0;
    cmp1_in1 <= x_1;

    cmp2_in0 <= x_3;
    cmp2_in1 <= x_4;

    cmp3_in0 <= x_6;
    cmp3_in1 <= x_7;
    

    r02_tmp <= x_2;
    r05_tmp <= x_5;
    r08_tmp <= x_8;
    r0[0] <= cmp1_out0;
    r0[1] <= cmp1_out1;
    r0[2] <= r02_tmp;
    r0[3] <= cmp2_out0;
    r0[4] <= cmp2_out1;
    r0[5] <= r05_tmp;
    r0[6] <= cmp3_out0;
    r0[7] <= cmp3_out1;
    r0[8] <= r08_tmp;


    cmp4_in0 <= r0[1];
    cmp4_in1 <= r0[2];
    
    cmp5_in0 <= r0[4];
    cmp5_in1 <= r0[5];

    cmp6_in0 <= r0[7];
    cmp6_in1 <= r0[8];

    r10_tmp <= r0[0];
    r13_tmp <= r0[3];
    r16_tmp <= r0[6];
    r1[0] <= r10_tmp;
    r1[1] <= cmp4_out0;
    r1[2] <= cmp4_out1;
    r1[3] <= r13_tmp;
    r1[4] <= cmp5_out0;
    r1[5] <= cmp5_out1;
    r1[6] <= r16_tmp;
    r1[7] <= cmp6_out0;
    r1[8] <= cmp6_out1;


    cmp7_in0 <= r1[0];
    cmp7_in1 <= r1[1];

    cmp8_in0 <= r1[3];
    cmp8_in1 <= r1[4];

    cmp9_in0 <= r1[6];
    cmp9_in1 <= r1[7];

    r22_tmp <= r1[2];
    r25_tmp <= r1[5];
    r28_tmp <= r1[8];
    r2[0] <= cmp7_out0;
    r2[1] <= cmp7_out1;
    r2[2] <= r22_tmp;
    r2[3] <= cmp8_out0;
    r2[4] <= cmp8_out1;
    r2[5] <= r25_tmp;
    r2[6] <= cmp9_out0;
    r2[7] <= cmp9_out1;
    r2[8] <= r28_tmp;


    cmp10_in0 <= r2[0];
    cmp10_in1 <= r2[3];
    
    cmp11_in0 <= r2[1];
    cmp11_in1 <= r2[4];

    cmp12_in0 <= r2[5];
    cmp12_in1 <= r2[8];


    r32_tmp <= r2[6];
    r35_tmp <= r2[7];
    r36_tmp <= r2[2];
  //r3[0] <= cmp10_out0;
    r3[1] <= cmp10_out1;
    r3[2] <= r32_tmp;
    r3[3] <= cmp11_out0;
    r3[4] <= cmp11_out1;
    r3[5] <= r35_tmp;
    r3[6] <= r36_tmp;
    r3[7] <= cmp12_out0;
  //r3[8] <= cmp12_out1;

    cmp13_in0 <= r3[1];
    cmp13_in1 <= r3[2];

    cmp14_in0 <= r3[4];
    cmp14_in1 <= r3[5];

    cmp15_in0 <= r3[6];
    cmp15_in1 <= r3[7];


    r43_tmp <= r3[3];
  //r4[0] <= cmp10_out0;
  //r4[1] <= cmp13_out0;
    r4[2] <= cmp13_out1;
    r4[3] <= r43_tmp;
    r4[4] <= cmp14_out0;
  //r4[5] <= cmp14_out1;
    r4[6] <= cmp15_out0;
  //r4[7] <= cmp15_out1;
  //r4[8] <= cmp12_out1;

    cmp16_in0 <= r4[3];
    cmp16_in1 <= r4[4];


    r52_tmp <= r4[2];
    r56_tmp <= r4[6];
  //r5[0] <= cmp10_out0;
  //r5[1] <= cmp13_out0;
    r5[2] <= r52_tmp;
    r5[3] <= cmp16_out0;
    r5[4] <= cmp16_out1;
  //r5[5] <= cmp14_out1; 
    r5[6] <= r56_tmp;
  //r5[7] <= cmp15_out1;
  //r5[8] <= cmp12_out1;

    cmp17_in0 = r5[2];
    cmp17_in1 = r5[4];


    r65_tmp <= r5[6];
  //r6[0] <= cmp10_out0;
  //r6[1] <= cmp13_out0;
  //r6[2] <= r4[2];
    r6[3] <= cmp17_out0;
    r6[4] <= cmp17_out1;
    r6[5] <= r65_tmp;  
  //r6[6] <= r4[6];
  //r6[7] <= cmp15_out1;
  //r6[8] <= cmp12_out1;


    cmp18_in0 <= r6[4];
    cmp18_in1 <= r6[5];


    r73_tmp <= r6[3];
  //r7[0] <= cmp10_out0;
  //r7[1] <= cmp13_out0;
  //r7[2] <= r4[2];
    r7[3] <= r73_tmp;
    r7[4] <= cmp18_out0;
  //r7[5] <= r5[6];  
  //r7[6] <= r4[6];
  //r7[7] <= cmp15_out1;
  //r7[8] <= cmp12_out1;

  cmp19_in0 <= r7[3];
  cmp19_in1 <= r7[4];
    
end

    assign median = cmp19_out1;

    cmp cmp1 (.in0(cmp1_in0), .in1(cmp1_in1), .out0(cmp1_out0), .out1(cmp1_out1));
    cmp cmp2 (.in0(cmp2_in0), .in1(cmp2_in1), .out0(cmp2_out0), .out1(cmp2_out1));
    cmp cmp3 (.in0(cmp3_in0), .in1(cmp3_in1), .out0(cmp3_out0), .out1(cmp3_out1));
    cmp cmp4 (.in0(cmp4_in0), .in1(cmp4_in1), .out0(cmp4_out0), .out1(cmp4_out1));
    cmp cmp5 (.in0(cmp5_in0), .in1(cmp5_in1), .out0(cmp5_out0), .out1(cmp5_out1));
    cmp cmp6 (.in0(cmp6_in0), .in1(cmp6_in1), .out0(cmp6_out0), .out1(cmp6_out1));
    cmp cmp7 (.in0(cmp7_in0), .in1(cmp7_in1), .out0(cmp7_out0), .out1(cmp7_out1));
    cmp cmp8 (.in0(cmp8_in0), .in1(cmp8_in1), .out0(cmp8_out0), .out1(cmp8_out1));
    cmp cmp9 (.in0(cmp9_in0), .in1(cmp9_in1), .out0(cmp9_out0), .out1(cmp9_out1));
    cmp cmp10 (.in0(cmp10_in0), .in1(cmp10_in1), .out0(cmp10_out0), .out1(cmp10_out1));
    cmp cmp11 (.in0(cmp11_in0), .in1(cmp11_in1), .out0(cmp11_out0), .out1(cmp11_out1));
    cmp cmp12 (.in0(cmp12_in0), .in1(cmp12_in1), .out0(cmp12_out0), .out1(cmp12_out1));
    cmp cmp13 (.in0(cmp13_in0), .in1(cmp13_in1), .out0(cmp13_out0), .out1(cmp13_out1));
    cmp cmp14 (.in0(cmp14_in0), .in1(cmp14_in1), .out0(cmp14_out0), .out1(cmp14_out1));
    cmp cmp15 (.in0(cmp15_in0), .in1(cmp15_in1), .out0(cmp15_out0), .out1(cmp15_out1));
    cmp cmp16 (.in0(cmp16_in0), .in1(cmp16_in1), .out0(cmp16_out0), .out1(cmp16_out1));
    cmp cmp17 (.in0(cmp17_in0), .in1(cmp17_in1), .out0(cmp17_out0), .out1(cmp17_out1));
    cmp cmp18 (.in0(cmp18_in0), .in1(cmp18_in1), .out0(cmp18_out0), .out1(cmp18_out1));
    cmp cmp19 (.in0(cmp19_in0), .in1(cmp19_in1), .out0(cmp19_out0), .out1(cmp19_out1));


endmodule


module cmp(
    input  [7:0] in0,
    input  [7:0] in1,
    output wire [7:0] out0,
    output wire [7:0] out1
);

    assign out0 = (in0<in1) ? in0:in1;
    assign out1 = (in0<in1) ? in1:in0; 
endmodule

gen_code/sort_pipe_test.v
module sort_test();
    reg clk;
    reg [7:0] x_0;
    reg [7:0] x_1;
    reg [7:0] x_2;
    reg [7:0] x_3;
    reg [7:0] x_4;
    reg [7:0] x_5;
    reg [7:0] x_6;
    reg [7:0] x_7;
    reg [7:0] x_8;
    wire [7:0] median;

initial begin
    clk = 0;
    forever #10 clk = ~clk;
end

initial begin
    #10
    x_0 = 9;
    x_1 = 8;
    x_2 = 7;
    x_3 = 6;
    x_4 = 5;
    x_5 = 4;
    x_6 = 3;
    x_7 = 2;
    x_8 = 1;
    
    #20
    
    x_0 = 19;
    x_1 = 18;
    x_2 = 17;
    x_3 = 16;
    x_4 = 11;
    x_5 = 12;
    x_6 = 13;
    x_7 = 14;
    x_8 = 15;
    /*

    #20
    x_0 = 29;
    x_1 = 28;
    x_2 = 27;
    x_3 = 26;
    x_4 = 21;
    x_5 = 22;
    x_6 = 23;
    x_7 = 24;
    x_8 = 25;
    */
end
initial begin
    #1000 $finish();
end

always @(posedge clk) begin
    $write("[%t] sort\n", $time);
end

initial begin
      $dumpfile("sort_pipe.vcd");
      $dumpvars(0, s_pipe);
end

sort_pipe s_pipe (
    .clk(clk),
    .x_0(x_0),
    .x_1(x_1),
    .x_2(x_2),
    .x_3(x_3),
    .x_4(x_4),
    .x_5(x_5),
    .x_6(x_6),
    .x_7(x_7),
    .x_8(x_8),
    .median(median)
);

endmodule

sort_pipe.vcd
$date
	Tue Oct 29 19:26:26 2019
$end
$version
	Icarus Verilog
$end
$timescale
	1s
$end
$scope module sort_test $end
$scope module s_pipe $end
$var wire 1 ! clk $end
$var wire 8 " median [7:0] $end
$var wire 8 # r0_out0 [7:0] $end
$var wire 8 $ x_0 [7:0] $end
$var wire 8 % x_1 [7:0] $end
$var wire 8 & x_2 [7:0] $end
$var wire 8 ' x_3 [7:0] $end
$var wire 8 ( x_4 [7:0] $end
$var wire 8 ) x_5 [7:0] $end
$var wire 8 * x_6 [7:0] $end
$var wire 8 + x_7 [7:0] $end
$var wire 8 , x_8 [7:0] $end
$var wire 8 - cmp9_out1 [7:0] $end
$var wire 8 . cmp9_out0 [7:0] $end
$var wire 8 / cmp8_out1 [7:0] $end
$var wire 8 0 cmp8_out0 [7:0] $end
$var wire 8 1 cmp7_out1 [7:0] $end
$var wire 8 2 cmp7_out0 [7:0] $end
$var wire 8 3 cmp6_out1 [7:0] $end
$var wire 8 4 cmp6_out0 [7:0] $end
$var wire 8 5 cmp5_out1 [7:0] $end
$var wire 8 6 cmp5_out0 [7:0] $end
$var wire 8 7 cmp4_out1 [7:0] $end
$var wire 8 8 cmp4_out0 [7:0] $end
$var wire 8 9 cmp3_out1 [7:0] $end
$var wire 8 : cmp3_out0 [7:0] $end
$var wire 8 ; cmp2_out1 [7:0] $end
$var wire 8 < cmp2_out0 [7:0] $end
$var wire 8 = cmp1_out1 [7:0] $end
$var wire 8 > cmp1_out0 [7:0] $end
$var wire 8 ? cmp19_out1 [7:0] $end
$var wire 8 @ cmp19_out0 [7:0] $end
$var wire 8 A cmp18_out1 [7:0] $end
$var wire 8 B cmp18_out0 [7:0] $end
$var wire 8 C cmp17_out1 [7:0] $end
$var wire 8 D cmp17_out0 [7:0] $end
$var wire 8 E cmp16_out1 [7:0] $end
$var wire 8 F cmp16_out0 [7:0] $end
$var wire 8 G cmp15_out1 [7:0] $end
$var wire 8 H cmp15_out0 [7:0] $end
$var wire 8 I cmp14_out1 [7:0] $end
$var wire 8 J cmp14_out0 [7:0] $end
$var wire 8 K cmp13_out1 [7:0] $end
$var wire 8 L cmp13_out0 [7:0] $end
$var wire 8 M cmp12_out1 [7:0] $end
$var wire 8 N cmp12_out0 [7:0] $end
$var wire 8 O cmp11_out1 [7:0] $end
$var wire 8 P cmp11_out0 [7:0] $end
$var wire 8 Q cmp10_out1 [7:0] $end
$var wire 8 R cmp10_out0 [7:0] $end
$var reg 8 S cmp10_in0 [7:0] $end
$var reg 8 T cmp10_in1 [7:0] $end
$var reg 8 U cmp11_in0 [7:0] $end
$var reg 8 V cmp11_in1 [7:0] $end
$var reg 8 W cmp12_in0 [7:0] $end
$var reg 8 X cmp12_in1 [7:0] $end
$var reg 8 Y cmp13_in0 [7:0] $end
$var reg 8 Z cmp13_in1 [7:0] $end
$var reg 8 [ cmp14_in0 [7:0] $end
$var reg 8 \ cmp14_in1 [7:0] $end
$var reg 8 ] cmp15_in0 [7:0] $end
$var reg 8 ^ cmp15_in1 [7:0] $end
$var reg 8 _ cmp16_in0 [7:0] $end
$var reg 8 ` cmp16_in1 [7:0] $end
$var reg 8 a cmp17_in0 [7:0] $end
$var reg 8 b cmp17_in1 [7:0] $end
$var reg 8 c cmp18_in0 [7:0] $end
$var reg 8 d cmp18_in1 [7:0] $end
$var reg 8 e cmp19_in0 [7:0] $end
$var reg 8 f cmp19_in1 [7:0] $end
$var reg 8 g cmp1_in0 [7:0] $end
$var reg 8 h cmp1_in1 [7:0] $end
$var reg 8 i cmp2_in0 [7:0] $end
$var reg 8 j cmp2_in1 [7:0] $end
$var reg 8 k cmp3_in0 [7:0] $end
$var reg 8 l cmp3_in1 [7:0] $end
$var reg 8 m cmp4_in0 [7:0] $end
$var reg 8 n cmp4_in1 [7:0] $end
$var reg 8 o cmp5_in0 [7:0] $end
$var reg 8 p cmp5_in1 [7:0] $end
$var reg 8 q cmp6_in0 [7:0] $end
$var reg 8 r cmp6_in1 [7:0] $end
$var reg 8 s cmp7_in0 [7:0] $end
$var reg 8 t cmp7_in1 [7:0] $end
$var reg 8 u cmp8_in0 [7:0] $end
$var reg 8 v cmp8_in1 [7:0] $end
$var reg 8 w cmp9_in0 [7:0] $end
$var reg 8 x cmp9_in1 [7:0] $end
$var reg 8 y r02_tmp [7:0] $end
$var reg 8 z r05_tmp [7:0] $end
$var reg 8 { r08_tmp [7:0] $end
$var reg 8 | r10_tmp [7:0] $end
$var reg 8 } r13_tmp [7:0] $end
$var reg 8 ~ r16_tmp [7:0] $end
$var reg 8 !" r22_tmp [7:0] $end
$var reg 8 "" r25_tmp [7:0] $end
$var reg 8 #" r28_tmp [7:0] $end
$var reg 8 $" r32_tmp [7:0] $end
$var reg 8 %" r35_tmp [7:0] $end
$var reg 8 &" r36_tmp [7:0] $end
$var reg 8 '" r43_tmp [7:0] $end
$var reg 8 (" r52_tmp [7:0] $end
$var reg 8 )" r56_tmp [7:0] $end
$var reg 8 *" r65_tmp [7:0] $end
$var reg 8 +" r73_tmp [7:0] $end
$scope module cmp1 $end
$var wire 8 ," in0 [7:0] $end
$var wire 8 -" in1 [7:0] $end
$var wire 8 ." out1 [7:0] $end
$var wire 8 /" out0 [7:0] $end
$upscope $end
$scope module cmp10 $end
$var wire 8 0" in0 [7:0] $end
$var wire 8 1" in1 [7:0] $end
$var wire 8 2" out1 [7:0] $end
$var wire 8 3" out0 [7:0] $end
$upscope $end
$scope module cmp11 $end
$var wire 8 4" in0 [7:0] $end
$var wire 8 5" in1 [7:0] $end
$var wire 8 6" out1 [7:0] $end
$var wire 8 7" out0 [7:0] $end
$upscope $end
$scope module cmp12 $end
$var wire 8 8" in0 [7:0] $end
$var wire 8 9" in1 [7:0] $end
$var wire 8 :" out1 [7:0] $end
$var wire 8 ;" out0 [7:0] $end
$upscope $end
$scope module cmp13 $end
$var wire 8 <" in0 [7:0] $end
$var wire 8 =" in1 [7:0] $end
$var wire 8 >" out1 [7:0] $end
$var wire 8 ?" out0 [7:0] $end
$upscope $end
$scope module cmp14 $end
$var wire 8 @" in0 [7:0] $end
$var wire 8 A" in1 [7:0] $end
$var wire 8 B" out1 [7:0] $end
$var wire 8 C" out0 [7:0] $end
$upscope $end
$scope module cmp15 $end
$var wire 8 D" in0 [7:0] $end
$var wire 8 E" in1 [7:0] $end
$var wire 8 F" out1 [7:0] $end
$var wire 8 G" out0 [7:0] $end
$upscope $end
$scope module cmp16 $end
$var wire 8 H" in0 [7:0] $end
$var wire 8 I" in1 [7:0] $end
$var wire 8 J" out1 [7:0] $end
$var wire 8 K" out0 [7:0] $end
$upscope $end
$scope module cmp17 $end
$var wire 8 L" in0 [7:0] $end
$var wire 8 M" in1 [7:0] $end
$var wire 8 N" out1 [7:0] $end
$var wire 8 O" out0 [7:0] $end
$upscope $end
$scope module cmp18 $end
$var wire 8 P" in0 [7:0] $end
$var wire 8 Q" in1 [7:0] $end
$var wire 8 R" out1 [7:0] $end
$var wire 8 S" out0 [7:0] $end
$upscope $end
$scope module cmp19 $end
$var wire 8 T" in0 [7:0] $end
$var wire 8 U" in1 [7:0] $end
$var wire 8 V" out1 [7:0] $end
$var wire 8 W" out0 [7:0] $end
$upscope $end
$scope module cmp2 $end
$var wire 8 X" in0 [7:0] $end
$var wire 8 Y" in1 [7:0] $end
$var wire 8 Z" out1 [7:0] $end
$var wire 8 [" out0 [7:0] $end
$upscope $end
$scope module cmp3 $end
$var wire 8 \" in0 [7:0] $end
$var wire 8 ]" in1 [7:0] $end
$var wire 8 ^" out1 [7:0] $end
$var wire 8 _" out0 [7:0] $end
$upscope $end
$scope module cmp4 $end
$var wire 8 `" in0 [7:0] $end
$var wire 8 a" in1 [7:0] $end
$var wire 8 b" out1 [7:0] $end
$var wire 8 c" out0 [7:0] $end
$upscope $end
$scope module cmp5 $end
$var wire 8 d" in0 [7:0] $end
$var wire 8 e" in1 [7:0] $end
$var wire 8 f" out1 [7:0] $end
$var wire 8 g" out0 [7:0] $end
$upscope $end
$scope module cmp6 $end
$var wire 8 h" in0 [7:0] $end
$var wire 8 i" in1 [7:0] $end
$var wire 8 j" out1 [7:0] $end
$var wire 8 k" out0 [7:0] $end
$upscope $end
$scope module cmp7 $end
$var wire 8 l" in0 [7:0] $end
$var wire 8 m" in1 [7:0] $end
$var wire 8 n" out1 [7:0] $end
$var wire 8 o" out0 [7:0] $end
$upscope $end
$scope module cmp8 $end
$var wire 8 p" in0 [7:0] $end
$var wire 8 q" in1 [7:0] $end
$var wire 8 r" out1 [7:0] $end
$var wire 8 s" out0 [7:0] $end
$upscope $end
$scope module cmp9 $end
$var wire 8 t" in0 [7:0] $end
$var wire 8 u" in1 [7:0] $end
$var wire 8 v" out1 [7:0] $end
$var wire 8 w" out0 [7:0] $end
$upscope $end
$upscope $end
$upscope $end
$enddefinitions $end
#0
$dumpvars
bx w"
bx v"
bx u"
bx t"
bx s"
bx r"
bx q"
bx p"
bx o"
bx n"
bx m"
bx l"
bx k"
bx j"
bx i"
bx h"
bx g"
bx f"
bx e"
bx d"
bx c"
bx b"
bx a"
bx `"
bx _"
bx ^"
bx ]"
bx \"
bx ["
bx Z"
bx Y"
bx X"
bx W"
bx V"
bx U"
bx T"
bx S"
bx R"
bx Q"
bx P"
bx O"
bx N"
bx M"
bx L"
bx K"
bx J"
bx I"
bx H"
bx G"
bx F"
bx E"
bx D"
bx C"
bx B"
bx A"
bx @"
bx ?"
bx >"
bx ="
bx <"
bx ;"
bx :"
bx 9"
bx 8"
bx 7"
bx 6"
bx 5"
bx 4"
bx 3"
bx 2"
bx 1"
bx 0"
bx /"
bx ."
bx -"
bx ,"
bx +"
bx *"
bx )"
bx ("
bx '"
bx &"
bx %"
bx $"
bx #"
bx ""
bx !"
bx ~
bx }
bx |
bx {
bx z
bx y
bx x
bx w
bx v
bx u
bx t
bx s
bx r
bx q
bx p
bx o
bx n
bx m
bx l
bx k
bx j
bx i
bx h
bx g
bx f
bx e
bx d
bx c
bx b
bx a
bx `
bx _
bx ^
bx ]
bx \
bx [
bx Z
bx Y
bx X
bx W
bx V
bx U
bx T
bx S
bx R
bx Q
bx P
bx O
bx N
bx M
bx L
bx K
bx J
bx I
bx H
bx G
bx F
bx E
bx D
bx C
bx B
bx A
bx @
bx ?
bx >
bx =
bx <
bx ;
bx :
bx 9
bx 8
bx 7
bx 6
bx 5
bx 4
bx 3
bx 2
bx 1
bx 0
bx /
bx .
bx -
bx ,
bx +
bx *
bx )
bx (
bx '
bx &
bx %
bx $
bx #
bx "
0!
$end
#10
b10 :
b10 _"
b11 9
b11 ^"
b101 <
b101 ["
b110 ;
b110 Z"
b1000 >
b1000 /"
b1001 =
b1001 ."
b1 {
b100 z
b111 y
b10 l
b10 ]"
b11 k
b11 \"
b101 j
b101 Y"
b110 i
b110 X"
b1000 h
b1000 -"
b1001 g
b1001 ,"
b1 ,
b10 +
b11 *
b100 )
b101 (
b110 '
b111 &
b1000 %
b1001 $
1!
#20
0!
#30
b1101 :
b1101 _"
b1110 9
b1110 ^"
b1011 <
b1011 ["
b10000 ;
b10000 Z"
b10010 >
b10010 /"
b10011 =
b10011 ."
b1000 #
b1111 {
b1100 z
b10001 y
b1110 l
b1110 ]"
b1101 k
b1101 \"
b1011 j
b1011 Y"
b10000 i
b10000 X"
b10010 h
b10010 -"
b10011 g
b10011 ,"
1!
b1111 ,
b1110 +
b1101 *
b1100 )
b1011 (
b10000 '
b10001 &
b10010 %
b10011 $
#40
0!
#50
b1 4
b1 k"
b11 3
b11 j"
b100 6
b100 g"
b110 5
b110 f"
b111 8
b111 c"
b1001 7
b1001 b"
b10 ~
b101 }
b1000 |
b1 r
b1 i"
b11 q
b11 h"
b100 p
b100 e"
b110 o
b110 d"
b111 n
b111 a"
b1001 m
b1001 `"
b10010 #
1!
#60
0!
#70
b1110 4
b1110 k"
b1111 3
b1111 j"
b1100 6
b1100 g"
b10000 5
b10000 f"
b10001 8
b10001 c"
b10011 7
b10011 b"
b1101 ~
b1011 }
b10010 |
b1111 r
b1111 i"
b1110 q
b1110 h"
b1100 p
b1100 e"
b10000 o
b10000 d"
b10001 n
b10001 a"
b10011 m
b10011 `"
1!
#80
0!
#90
b1 .
b1 w"
b10 -
b10 v"
b100 0
b100 s"
b101 /
b101 r"
b111 2
b111 o"
b1000 1
b1000 n"
b11 #"
b110 ""
b1001 !"
b1 x
b1 u"
b10 w
b10 t"
b100 v
b100 q"
b101 u
b101 p"
b111 t
b111 m"
b1000 s
b1000 l"
1!
#100
0!
#110
b1101 .
b1101 w"
b1110 -
b1110 v"
b1011 0
b1011 s"
b1100 /
b1100 r"
b10001 2
b10001 o"
b10010 1
b10010 n"
b1111 #"
b10000 ""
b10011 !"
b1110 x
b1110 u"
b1101 w
b1101 t"
b1100 v
b1100 q"
b1011 u
b1011 p"
b10001 t
b10001 m"
b10010 s
b10010 l"
1!
#120
0!
#130
b11 N
b11 ;"
b110 M
b110 :"
b101 P
b101 7"
b1000 O
b1000 6"
b100 R
b100 3"
b111 Q
b111 2"
b1001 &"
b10 %"
b1 $"
b11 X
b11 9"
b110 W
b110 8"
b101 V
b101 5"
b1000 U
b1000 4"
b100 T
b100 1"
b111 S
b111 0"
1!
#140
0!
#150
b1111 N
b1111 ;"
b10000 M
b10000 :"
b1100 P
b1100 7"
b10010 O
b10010 6"
b1011 R
b1011 3"
b10001 Q
b10001 2"
b10011 &"
b1110 %"
b1101 $"
b1111 X
b1111 9"
b10000 W
b10000 8"
b1100 V
b1100 5"
b10010 U
b10010 4"
b1011 T
b1011 1"
b10001 S
b10001 0"
1!
#160
0!
#170
b11 H
b11 G"
b1001 G
b1001 F"
b10 J
b10 C"
b1000 I
b1000 B"
b1 L
b1 ?"
b111 K
b111 >"
b101 '"
b11 ^
b11 E"
b1001 ]
b1001 D"
b10 \
b10 A"
b1000 [
b1000 @"
b1 Z
b1 ="
b111 Y
b111 <"
1!
#180
0!
#190
b1111 H
b1111 G"
b10011 G
b10011 F"
b1110 J
b1110 C"
b10010 I
b10010 B"
b1101 L
b1101 ?"
b10001 K
b10001 >"
b1100 '"
b1111 ^
b1111 E"
b10011 ]
b10011 D"
b1110 \
b1110 A"
b10010 [
b10010 @"
b1101 Z
b1101 ="
b10001 Y
b10001 <"
1!
#200
0!
#210
b10 F
b10 K"
b101 E
b101 J"
b11 )"
b111 ("
b10 `
b10 I"
b101 _
b101 H"
1!
#220
0!
#230
b1100 F
b1100 K"
b1110 E
b1110 J"
b1111 )"
b10001 ("
b1110 `
b1110 I"
b1100 _
b1100 H"
1!
#240
0!
#250
b11 *"
b101 D
b101 O"
b111 C
b111 N"
b101 b
b101 M"
b111 a
b111 L"
1!
#260
0!
#270
b1111 *"
b1110 D
b1110 O"
b10001 C
b10001 N"
b1110 b
b1110 M"
b10001 a
b10001 L"
1!
#280
0!
#290
b11 B
b11 S"
b111 A
b111 R"
b101 +"
b11 d
b11 Q"
b111 c
b111 P"
1!
#300
0!
#310
b1111 B
b1111 S"
b10001 A
b10001 R"
b1110 +"
b1111 d
b1111 Q"
b10001 c
b10001 P"
1!
#320
0!
#330
b11 @
b11 W"
b101 "
b101 ?
b101 V"
b11 f
b11 U"
b101 e
b101 T"
1!
#340
0!
#350
b1110 @
b1110 W"
b1111 "
b1111 ?
b1111 V"
b1111 f
b1111 U"
b1110 e
b1110 T"
1!
